{
  "_class": "shapePath",
  "booleanOperation": 0,
  "clippingMaskMode": 0,
  "do_objectID": "DCCEF517-A71F-4AFB-928A-74BC93B5410D",
  "edited": true,
  "exportOptions": {
    "_class": "exportOptions",
    "do_objectID": "2C163EB7-D823-4AC4-882B-80045526A2B1",
    "exportFormats": [
    ],
    "includedLayerIds": [
    ],
    "layerOptions": 0,
    "shouldTrim": false
  },
  "frame": {
    "_class": "rect",
    "constrainProportions": false,
    "do_objectID": "C1D32292-9A82-4022-9B11-AD569BE7FBB6",
    "height": 2.046139534883725,
    "width": 2.038584269662918,
    "x": 63.87105505617973,
    "y": 77.86996512349977
  },
  "hasClippingMask": false,
  "isClosed": false,
  "isFixedToViewport": false,
  "isFlippedHorizontal": false,
  "isFlippedVertical": false,
  "isLocked": false,
  "isVisible": true,
  "layerListExpandedType": 0,
  "name": "Fill 21",
  "nameIsFixed": false,
  "pointRadiusBehaviour": 1,
  "points": [
    {
      "_class": "curvePoint",
      "cornerRadius": 0,
      "curveFrom": "{0.76973444889050691, 0}",
      "curveMode": 4,
      "curveTo": "{0.49690796653328556, 0}",
      "hasCurveFrom": true,
      "hasCurveTo": false,
      "point": "{0.49690796653328556, 0}"
    },
    {
      "_class": "curvePoint",
      "cornerRadius": 0,
      "curveFrom": "{1, 0.77577741407528633}",
      "curveMode": 2,
      "curveTo": "{1, 0.23040552827786875}",
      "hasCurveFrom": true,
      "hasCurveTo": true,
      "point": "{1, 0.50318239679941801}"
    },
    {
      "_class": "curvePoint",
      "cornerRadius": 0,
      "curveFrom": "{0.22426336849763664, 1}",
      "curveMode": 2,
      "curveTo": "{0.76973444889050691, 1}",
      "hasCurveFrom": true,
      "hasCurveTo": true,
      "point": "{0.49690796653328556, 1}"
    },
    {
      "_class": "curvePoint",
      "cornerRadius": 0,
      "curveFrom": "{0, 0.23040552827786875}",
      "curveMode": 2,
      "curveTo": "{0, 0.77577741407528633}",
      "hasCurveFrom": true,
      "hasCurveTo": true,
      "point": "{0, 0.50318239679941801}"
    },
    {
      "_class": "curvePoint",
      "cornerRadius": 0,
      "curveFrom": "{0.49690796653328556, 0}",
      "curveMode": 4,
      "curveTo": "{0.22426336849763664, 0}",
      "hasCurveFrom": false,
      "hasCurveTo": true,
      "point": "{0.49690796653328556, 0}"
    }
  ],
  "resizingConstraint": 63,
  "resizingType": 0,
  "rotation": 0,
  "shouldBreakMaskChain": false,
  "style": {
    "_class": "style",
    "blur": {
      "_class": "blur",
      "center": "{0.5, 0.5}",
      "do_objectID": "86C8FBFE-C59C-40F9-A553-E71BEE6808AA",
      "isEnabled": false,
      "motionAngle": 0,
      "radius": 3.707865168539326,
      "saturation": 1,
      "type": 0
    },
    "do_objectID": "4414C990-2B5B-4B12-ACF4-96A6C64B2BA3",
    "endMarkerType": 0,
    "fills": [
      {
        "_class": "fill",
        "color": {
          "_class": "color",
          "alpha": 1,
          "blue": 0.2761964499950409,
          "green": 0.7273640036582947,
          "red": 0.3603302538394928
        },
        "fillType": 0,
        "isEnabled": true,
        "noiseIndex": 0,
        "noiseIntensity": 0,
        "patternFillType": 1,
        "patternTileScale": 1
      }
    ],
    "miterLimit": 10,
    "startMarkerType": 0,
    "windingRule": 1
  }
}